LICENSE
README.md
setup.cfg
setup.py
Mulguisin/__init__.py
Mulguisin/get_density.py
Mulguisin/mgs_class.py
Mulguisin/mgs_code.py
Mulguisin.egg-info/PKG-INFO
Mulguisin.egg-info/SOURCES.txt
Mulguisin.egg-info/dependency_links.txt
Mulguisin.egg-info/requires.txt
Mulguisin.egg-info/top_level.txt