Metadata-Version: 2.1
Name: Mulguisin
Version: 0.91
Summary: Mulguisin: Cluster/group finding algorithm
Home-page: https://github.com/youngju20/Mulguisin
Author: Young Ju, Inkyu Park, Sungwook E. Hong, Cristiano G. Sabiu
Author-email: youngju@uos.ac.kr
License: BSD
License-File: LICENSE
